[
    {
        "itemId": 212446,
        "encounterId": 2607,
        "catalyzedItemId": 211979
    },
    {
        "itemId": 225574,
        "encounterId": 2609,
        "catalyzedItemId": 211979
    },
    {
        "itemId": 212437,
        "encounterId": 2609,
        "catalyzedItemId": 211980
    },
    {
        "itemId": 225587,
        "encounterId": 2602,
        "catalyzedItemId": 211980
    },
    {
        "itemId": 212442,
        "encounterId": 2607,
        "catalyzedItemId": 211981
    },
    {
        "itemId": 225589,
        "encounterId": 2601,
        "catalyzedItemId": 211981
    },
    {
        "itemId": 225590,
        "encounterId": 2611,
        "catalyzedItemId": 211986
    },
    {
        "itemId": 212443,
        "encounterId": 2608,
        "catalyzedItemId": 211986
    },
    {
        "itemId": 225744,
        "encounterId": -67,
        "catalyzedItemId": 211986
    },
    {
        "itemId": 212446,
        "encounterId": 2607,
        "catalyzedItemId": 211988
    },
    {
        "itemId": 225574,
        "encounterId": 2609,
        "catalyzedItemId": 211988
    },
    {
        "itemId": 212437,
        "encounterId": 2609,
        "catalyzedItemId": 211989
    },
    {
        "itemId": 225587,
        "encounterId": 2602,
        "catalyzedItemId": 211989
    },
    {
        "itemId": 212442,
        "encounterId": 2607,
        "catalyzedItemId": 211990
    },
    {
        "itemId": 225589,
        "encounterId": 2601,
        "catalyzedItemId": 211990
    },
    {
        "itemId": 225590,
        "encounterId": 2611,
        "catalyzedItemId": 211995
    },
    {
        "itemId": 212443,
        "encounterId": 2608,
        "catalyzedItemId": 211995
    },
    {
        "itemId": 225744,
        "encounterId": -67,
        "catalyzedItemId": 211995
    },
    {
        "itemId": 212446,
        "encounterId": 2607,
        "catalyzedItemId": 211997
    },
    {
        "itemId": 225574,
        "encounterId": 2609,
        "catalyzedItemId": 211997
    },
    {
        "itemId": 212437,
        "encounterId": 2609,
        "catalyzedItemId": 211998
    },
    {
        "itemId": 225587,
        "encounterId": 2602,
        "catalyzedItemId": 211998
    },
    {
        "itemId": 212442,
        "encounterId": 2607,
        "catalyzedItemId": 211999
    },
    {
        "itemId": 225589,
        "encounterId": 2601,
        "catalyzedItemId": 211999
    },
    {
        "itemId": 225590,
        "encounterId": 2611,
        "catalyzedItemId": 212004
    },
    {
        "itemId": 212443,
        "encounterId": 2608,
        "catalyzedItemId": 212004
    },
    {
        "itemId": 225744,
        "encounterId": -67,
        "catalyzedItemId": 212004
    },
    {
        "itemId": 212446,
        "encounterId": 2607,
        "catalyzedItemId": 212006
    },
    {
        "itemId": 225574,
        "encounterId": 2609,
        "catalyzedItemId": 212006
    },
    {
        "itemId": 212415,
        "encounterId": 2599,
        "catalyzedItemId": 212007
    },
    {
        "itemId": 225581,
        "encounterId": 2601,
        "catalyzedItemId": 212007
    },
    {
        "itemId": 212414,
        "encounterId": 2611,
        "catalyzedItemId": 212008
    },
    {
        "itemId": 225580,
        "encounterId": 2612,
        "catalyzedItemId": 212008
    },
    {
        "itemId": 225725,
        "encounterId": -67,
        "catalyzedItemId": 212008
    },
    {
        "itemId": 212431,
        "encounterId": 2607,
        "catalyzedItemId": 212013
    },
    {
        "itemId": 225586,
        "encounterId": 2609,
        "catalyzedItemId": 212013
    },
    {
        "itemId": 212446,
        "encounterId": 2607,
        "catalyzedItemId": 212015
    },
    {
        "itemId": 225574,
        "encounterId": 2609,
        "catalyzedItemId": 212015
    },
    {
        "itemId": 212415,
        "encounterId": 2599,
        "catalyzedItemId": 212016
    },
    {
        "itemId": 225581,
        "encounterId": 2601,
        "catalyzedItemId": 212016
    },
    {
        "itemId": 212414,
        "encounterId": 2611,
        "catalyzedItemId": 212017
    },
    {
        "itemId": 225580,
        "encounterId": 2612,
        "catalyzedItemId": 212017
    },
    {
        "itemId": 225725,
        "encounterId": -67,
        "catalyzedItemId": 212017
    },
    {
        "itemId": 212431,
        "encounterId": 2607,
        "catalyzedItemId": 212022
    },
    {
        "itemId": 225586,
        "encounterId": 2609,
        "catalyzedItemId": 212022
    },
    {
        "itemId": 212446,
        "encounterId": 2607,
        "catalyzedItemId": 212024
    },
    {
        "itemId": 225574,
        "encounterId": 2609,
        "catalyzedItemId": 212024
    },
    {
        "itemId": 212415,
        "encounterId": 2599,
        "catalyzedItemId": 212025
    },
    {
        "itemId": 225581,
        "encounterId": 2601,
        "catalyzedItemId": 212025
    },
    {
        "itemId": 212414,
        "encounterId": 2611,
        "catalyzedItemId": 212026
    },
    {
        "itemId": 225580,
        "encounterId": 2612,
        "catalyzedItemId": 212026
    },
    {
        "itemId": 225725,
        "encounterId": -67,
        "catalyzedItemId": 212026
    },
    {
        "itemId": 212431,
        "encounterId": 2607,
        "catalyzedItemId": 212031
    },
    {
        "itemId": 225586,
        "encounterId": 2609,
        "catalyzedItemId": 212031
    },
    {
        "itemId": 212446,
        "encounterId": 2607,
        "catalyzedItemId": 212033
    },
    {
        "itemId": 225574,
        "encounterId": 2609,
        "catalyzedItemId": 212033
    },
    {
        "itemId": 212438,
        "encounterId": 2611,
        "catalyzedItemId": 212034
    },
    {
        "itemId": 225588,
        "encounterId": 2612,
        "catalyzedItemId": 212034
    },
    {
        "itemId": 212425,
        "encounterId": 2607,
        "catalyzedItemId": 212035
    },
    {
        "itemId": 225583,
        "encounterId": 2609,
        "catalyzedItemId": 212035
    },
    {
        "itemId": 225723,
        "encounterId": -67,
        "catalyzedItemId": 212035
    },
    {
        "itemId": 212445,
        "encounterId": 2599,
        "catalyzedItemId": 212040
    },
    {
        "itemId": 225591,
        "encounterId": 2601,
        "catalyzedItemId": 212040
    },
    {
        "itemId": 212446,
        "encounterId": 2607,
        "catalyzedItemId": 212042
    },
    {
        "itemId": 225574,
        "encounterId": 2609,
        "catalyzedItemId": 212042
    },
    {
        "itemId": 212438,
        "encounterId": 2611,
        "catalyzedItemId": 212043
    },
    {
        "itemId": 225588,
        "encounterId": 2612,
        "catalyzedItemId": 212043
    },
    {
        "itemId": 212425,
        "encounterId": 2607,
        "catalyzedItemId": 212044
    },
    {
        "itemId": 225583,
        "encounterId": 2609,
        "catalyzedItemId": 212044
    },
    {
        "itemId": 225723,
        "encounterId": -67,
        "catalyzedItemId": 212044
    },
    {
        "itemId": 212445,
        "encounterId": 2599,
        "catalyzedItemId": 212049
    },
    {
        "itemId": 225591,
        "encounterId": 2601,
        "catalyzedItemId": 212049
    },
    {
        "itemId": 212446,
        "encounterId": 2607,
        "catalyzedItemId": 212051
    },
    {
        "itemId": 225574,
        "encounterId": 2609,
        "catalyzedItemId": 212051
    },
    {
        "itemId": 212438,
        "encounterId": 2611,
        "catalyzedItemId": 212052
    },
    {
        "itemId": 225588,
        "encounterId": 2612,
        "catalyzedItemId": 212052
    },
    {
        "itemId": 212425,
        "encounterId": 2607,
        "catalyzedItemId": 212053
    },
    {
        "itemId": 225583,
        "encounterId": 2609,
        "catalyzedItemId": 212053
    },
    {
        "itemId": 225723,
        "encounterId": -67,
        "catalyzedItemId": 212053
    },
    {
        "itemId": 212445,
        "encounterId": 2599,
        "catalyzedItemId": 212058
    },
    {
        "itemId": 225591,
        "encounterId": 2601,
        "catalyzedItemId": 212058
    },
    {
        "itemId": 212446,
        "encounterId": 2607,
        "catalyzedItemId": 212060
    },
    {
        "itemId": 225574,
        "encounterId": 2609,
        "catalyzedItemId": 212060
    },
    {
        "itemId": 212438,
        "encounterId": 2611,
        "catalyzedItemId": 212061
    },
    {
        "itemId": 225588,
        "encounterId": 2612,
        "catalyzedItemId": 212061
    },
    {
        "itemId": 212425,
        "encounterId": 2607,
        "catalyzedItemId": 212062
    },
    {
        "itemId": 225583,
        "encounterId": 2609,
        "catalyzedItemId": 212062
    },
    {
        "itemId": 225723,
        "encounterId": -67,
        "catalyzedItemId": 212062
    },
    {
        "itemId": 212445,
        "encounterId": 2599,
        "catalyzedItemId": 212067
    },
    {
        "itemId": 225591,
        "encounterId": 2601,
        "catalyzedItemId": 212067
    },
    {
        "itemId": 212446,
        "encounterId": 2607,
        "catalyzedItemId": 212069
    },
    {
        "itemId": 225574,
        "encounterId": 2609,
        "catalyzedItemId": 212069
    },
    {
        "itemId": 212426,
        "encounterId": 2607,
        "catalyzedItemId": 212070
    },
    {
        "itemId": 225584,
        "encounterId": 2608,
        "catalyzedItemId": 212070
    },
    {
        "itemId": 212430,
        "encounterId": 2611,
        "catalyzedItemId": 212071
    },
    {
        "itemId": 225585,
        "encounterId": 2602,
        "catalyzedItemId": 212071
    },
    {
        "itemId": 212416,
        "encounterId": 2599,
        "catalyzedItemId": 212076
    },
    {
        "itemId": 225582,
        "encounterId": 2612,
        "catalyzedItemId": 212076
    },
    {
        "itemId": 225721,
        "encounterId": -67,
        "catalyzedItemId": 212076
    },
    {
        "itemId": 212446,
        "encounterId": 2607,
        "catalyzedItemId": 212078
    },
    {
        "itemId": 225574,
        "encounterId": 2609,
        "catalyzedItemId": 212078
    },
    {
        "itemId": 212426,
        "encounterId": 2607,
        "catalyzedItemId": 212079
    },
    {
        "itemId": 225584,
        "encounterId": 2608,
        "catalyzedItemId": 212079
    },
    {
        "itemId": 212430,
        "encounterId": 2611,
        "catalyzedItemId": 212080
    },
    {
        "itemId": 225585,
        "encounterId": 2602,
        "catalyzedItemId": 212080
    },
    {
        "itemId": 212416,
        "encounterId": 2599,
        "catalyzedItemId": 212085
    },
    {
        "itemId": 225582,
        "encounterId": 2612,
        "catalyzedItemId": 212085
    },
    {
        "itemId": 225721,
        "encounterId": -67,
        "catalyzedItemId": 212085
    },
    {
        "itemId": 212446,
        "encounterId": 2607,
        "catalyzedItemId": 212087
    },
    {
        "itemId": 225574,
        "encounterId": 2609,
        "catalyzedItemId": 212087
    },
    {
        "itemId": 212426,
        "encounterId": 2607,
        "catalyzedItemId": 212088
    },
    {
        "itemId": 225584,
        "encounterId": 2608,
        "catalyzedItemId": 212088
    },
    {
        "itemId": 212430,
        "encounterId": 2611,
        "catalyzedItemId": 212089
    },
    {
        "itemId": 225585,
        "encounterId": 2602,
        "catalyzedItemId": 212089
    },
    {
        "itemId": 212416,
        "encounterId": 2599,
        "catalyzedItemId": 212094
    },
    {
        "itemId": 225582,
        "encounterId": 2612,
        "catalyzedItemId": 212094
    },
    {
        "itemId": 225721,
        "encounterId": -67,
        "catalyzedItemId": 212094
    }
]
